fuselage/__init__.py
fuselage/argument.py
fuselage/builder.py
fuselage/bundle.py
fuselage/changes/__init__.py
fuselage/changes/attributes.py
fuselage/changes/base.py
fuselage/changes/directory.py
fuselage/changes/execute.py
fuselage/changes/file.py
fuselage/contrib/__init__.py
fuselage/contrib/fabric.py
fuselage/contrib/libcloud.py
fuselage/defaults.py
fuselage/docker.py
fuselage/error.py
fuselage/event.py
fuselage/log.py
fuselage/platform.py
fuselage/policy.py
fuselage/provider.py
fuselage/providers/__init__.py
fuselage/providers/apt.py
fuselage/providers/directory.py
fuselage/providers/execute.py
fuselage/providers/files.py
fuselage/providers/git.py
fuselage/providers/group.py
fuselage/providers/line.py
fuselage/providers/link.py
fuselage/providers/mercurial.py
fuselage/providers/mount.py
fuselage/providers/mounted.py
fuselage/providers/patch.py
fuselage/providers/service.py
fuselage/providers/subversion.py
fuselage/providers/user.py
fuselage/providers/yum.py
fuselage/resource.py
fuselage/resources/__init__.py
fuselage/resources/checkout.py
fuselage/resources/directory.py
fuselage/resources/execute.py
fuselage/resources/file.py
fuselage/resources/group.py
fuselage/resources/line.py
fuselage/resources/link.py
fuselage/resources/mount.py
fuselage/resources/package.py
fuselage/resources/patch.py
fuselage/resources/service.py
fuselage/resources/special.py
fuselage/resources/user.py
fuselage/runner.py
fuselage/ssh.py
fuselage/utils.py
fuselage-3.1.2.dist-info/METADATA
fuselage-3.1.2.dist-info/WHEEL
fuselage-3.1.2.dist-info/entry_points.txt
fuselage-3.1.2.dist-info/RECORD
