Metadata-Version: 2.1
Name: fuselage
Version: 3.1.2
Summary: Orchestration and configuration management in Python
Home-page: https://github.com/yaybu/fuselage
License: Apache-2.0
Keywords: devops,automation
Author: Isotoma Limited
Author-email: support@isotoma.com
Requires-Python: >=3.8.1,<4.0.0
Classifier: Intended Audience :: System Administrators
Classifier: License :: OSI Approved :: Apache Software License
Classifier: Programming Language :: Python :: 3
Classifier: Programming Language :: Python :: 3.9
Classifier: Programming Language :: Python :: 3.10
Classifier: Programming Language :: Python :: 3.11
Classifier: Programming Language :: Python :: 3.7
Classifier: Programming Language :: Python :: 3.8
Classifier: Programming Language :: Python :: 3.9
Provides-Extra: ssh
Requires-Dist: paramiko (>=2.7.2,<3.0.0) ; extra == "ssh"
Project-URL: Repository, https://github.com/yaybu/fuselage
